jupyterlab_material_night_eighties/__init__.py
jupyterlab_material_night_eighties/_version.py
jupyterlab_material_night_eighties-0.3.3.data/data/share/jupyter/labextensions/@ninerealmlabs/jupyterlab_material_night_eighties/package.json
jupyterlab_material_night_eighties-0.3.3.data/data/share/jupyter/labextensions/@ninerealmlabs/jupyterlab_material_night_eighties/static/549.62f756cbe87b4e449ae2.js
jupyterlab_material_night_eighties-0.3.3.data/data/share/jupyter/labextensions/@ninerealmlabs/jupyterlab_material_night_eighties/static/568.e0a5e3eafad49886fdd8.js
jupyterlab_material_night_eighties-0.3.3.data/data/share/jupyter/labextensions/@ninerealmlabs/jupyterlab_material_night_eighties/static/remoteEntry.49e51651888cbe6f590d.js
jupyterlab_material_night_eighties-0.3.3.data/data/share/jupyter/labextensions/@ninerealmlabs/jupyterlab_material_night_eighties/static/style.js
jupyterlab_material_night_eighties-0.3.3.data/data/share/jupyter/labextensions/@ninerealmlabs/jupyterlab_material_night_eighties/static/third-party-licenses.json
jupyterlab_material_night_eighties-0.3.3.data/data/share/jupyter/labextensions/@ninerealmlabs/jupyterlab_material_night_eighties/themes/@ninerealmlabs/jupyterlab_material_night_eighties/index.css
jupyterlab_material_night_eighties-0.3.3.data/data/share/jupyter/labextensions/@ninerealmlabs/jupyterlab_material_night_eighties/themes/@ninerealmlabs/jupyterlab_material_night_eighties/index.js
jupyterlab_material_night_eighties-0.3.3.data/data/share/jupyter/labextensions/@ninerealmlabs/jupyterlab_material_night_eighties/install.json
jupyterlab_material_night_eighties-0.3.3.dist-info/METADATA
jupyterlab_material_night_eighties-0.3.3.dist-info/WHEEL
jupyterlab_material_night_eighties-0.3.3.dist-info/licenses/LICENSE
jupyterlab_material_night_eighties-0.3.3.dist-info/RECORD
