Metadata-Version: 2.1
Name: jupyterlab_material_night_eighties
Version: 0.3.3
Summary: A jupyterlab theme inspired by material darker and VSCode's material night eighties
Project-URL: Homepage, https://github.com/ninerealmlabs/jupyterlab-theme-material-night-eighties
Project-URL: Bug Tracker, https://github.com/ninerealmlabs/jupyterlab-theme-material-night-eighties/issues
Project-URL: Repository, https://github.com/ninerealmlabs/jupyterlab-theme-material-night-eighties.git
Author-email: ninerealmlabs <code@mail.ninerealmlabs.com>
License: BSD 3-Clause License
License-File: LICENSE
Classifier: Framework :: Jupyter
Classifier: Framework :: Jupyter :: JupyterLab
Classifier: Framework :: Jupyter :: JupyterLab :: 3
Classifier: Framework :: Jupyter :: JupyterLab :: Extensions
Classifier: Framework :: Jupyter :: JupyterLab :: Extensions :: Prebuilt
Classifier: License :: OSI Approved :: BSD License
Classifier: Programming Language :: Python
Classifier: Programming Language :: Python :: 3
Classifier: Programming Language :: Python :: 3.7
Classifier: Programming Language :: Python :: 3.8
Classifier: Programming Language :: Python :: 3.9
Classifier: Programming Language :: Python :: 3.10
Classifier: Programming Language :: Python :: 3.11
Requires-Python: >=3.7
Provides-Extra: test
Requires-Dist: coverage; extra == 'test'
Requires-Dist: pytest; extra == 'test'
Requires-Dist: pytest-asyncio; extra == 'test'
Requires-Dist: pytest-cov; extra == 'test'
Requires-Dist: pytest-tornasync; extra == 'test'
